lightnimage
