Metadata-Version: 1.2
Name: lightnimage
Version: 0.0.0.13
Summary: A library to analyze images of lightning strikes
Home-page: https://github.com/the16thpythonist/lightnimage
Author: Jonas Teufel
Author-email: jonseb1998@gmail.com
License: MIT
Platform: UNKNOWN
Requires-Python: ~=3.5
